{"chunk_definitions":[{"row":12,"row_count":1,"visible":true,"expansion_state":0,"options":{"engine":"r","label":"setup","include":false},"document_id":"FD3CDD1A","chunk_id":"csetup_chunk","chunk_label":"setup"},{"row":23,"row_count":1,"visible":true,"expansion_state":0,"options":{"engine":"r","label":"package_install","echo":false},"document_id":"FD3CDD1A","chunk_id":"c1ho5ejp26zdi","chunk_label":"package_install"},{"row":38,"row_count":1,"visible":true,"expansion_state":0,"options":{"engine":"r","label":"set variables and functions"},"document_id":"FD3CDD1A","chunk_id":"cjbj7z90ltss6","chunk_label":"set variables and functions"},{"row":73,"row_count":1,"visible":true,"expansion_state":0,"options":{"engine":"r","label":"unnamed-chunk-1"},"document_id":"FD3CDD1A","chunk_id":"c1hdgr61nqwfd","chunk_label":"unnamed-chunk-1"},{"row":82,"row_count":1,"visible":true,"expansion_state":0,"options":{"engine":"r","label":"init_tibble"},"document_id":"FD3CDD1A","chunk_id":"cwkfvkdns1k8g","chunk_label":"init_tibble"},{"row":150,"row_count":1,"visible":true,"expansion_state":0,"options":{"engine":"r","label":"grants"},"document_id":"FD3CDD1A","chunk_id":"cofmq9ywmorpt","chunk_label":"grants"},{"row":154,"row_count":1,"visible":true,"expansion_state":0,"options":{"engine":"r","label":"save_df"},"document_id":"FD3CDD1A","chunk_id":"cogkuaxh40d1z","chunk_label":"save_df"},{"row":207,"row_count":1,"visible":true,"expansion_state":0,"options":{"engine":"r","label":"experimental_scaping"},"document_id":"FD3CDD1A","chunk_id":"cjmbaxtlau8t2","chunk_label":"experimental_scaping"},{"row":217,"row_count":1,"visible":true,"expansion_state":0,"options":{"engine":"r","label":"df_definition"},"document_id":"FD3CDD1A","chunk_id":"cb9fb3n0n9tu1","chunk_label":"df_definition"},{"row":268,"row_count":1,"visible":true,"expansion_state":0,"options":{"engine":"r","label":"unnamed-chunk-3"},"document_id":"4076B90B","chunk_id":"c8x9golal7l83","chunk_label":"unnamed-chunk-2"},{"row":279,"row_count":1,"visible":true,"expansion_state":0,"options":{"engine":"r","label":"unnamed-chunk-8"},"document_id":"4076B90B","chunk_id":"c1oakom44uceh","chunk_label":"unnamed-chunk-3"},{"row":283,"row_count":1,"visible":true,"expansion_state":0,"options":{"engine":"r","label":"unnamed-chunk-7"},"document_id":"4076B90B","chunk_id":"c8e8x189jmjmy","chunk_label":"unnamed-chunk-4"}],"doc_write_time":1625250199}