{"chunk_definitions":[{"row":9,"row_count":1,"visible":true,"expansion_state":0,"options":{"engine":"r","label":"setup","include":false},"document_id":"F19C6478","chunk_id":"csetup_chunk","chunk_label":"setup"},{"row":93,"row_count":1,"visible":true,"expansion_state":0,"options":{"engine":"r","label":"import_and_clean_base_project_df"},"document_id":"F19C6478","chunk_id":"c7ojh6l3c40sy","chunk_label":"import_and_clean_base_project_df"},{"row":104,"row_count":1,"visible":true,"expansion_state":0,"options":{"engine":"r","label":"unnamed-chunk-226"},"document_id":"F19C6478","chunk_id":"cmzut190fei2u","chunk_label":"unnamed-chunk-2"},{"row":167,"row_count":1,"visible":true,"expansion_state":0,"options":{"engine":"r","label":"unnamed-chunk-229"},"document_id":"F19C6478","chunk_id":"c3reqosns613a","chunk_label":"unnamed-chunk-3"},{"row":179,"row_count":1,"visible":true,"expansion_state":0,"options":{"engine":"r","label":"unnamed-chunk-166"},"document_id":"F19C6478","chunk_id":"ceaf8525gfxih","chunk_label":"unnamed-chunk-4"}],"doc_write_time":1624667077}